wireless_demo/__init__.py
wireless_demo/controls.py
wireless_demo/demo_sd_sdk.py
wireless_demo/demo_ui.css
wireless_demo/demo_ui.py
wireless_demo/main.py
wireless_demo/pyinstaller.py
sd_wireless_demo-0.2.3.dist-info/LICENSE
sd_wireless_demo-0.2.3.dist-info/METADATA
sd_wireless_demo-0.2.3.dist-info/WHEEL
sd_wireless_demo-0.2.3.dist-info/entry_points.txt
sd_wireless_demo-0.2.3.dist-info/RECORD
