Metadata-Version: 2.1
Name: sd-wireless-demo
Version: 0.2.3
Summary: Wireless demo using the Sound Designer SDK on Windows
License: MIT
Author: Mark Melvin
Author-email: mark.melvin@onsemi.com
Requires-Python: >=3.8,<3.13
Classifier: Development Status :: 4 - Beta
Classifier: Environment :: Console
Classifier: Intended Audience :: Developers
Classifier: License :: OSI Approved :: MIT License
Classifier: Operating System :: Microsoft :: Windows :: Windows 10
Classifier: Operating System :: Microsoft :: Windows :: Windows 11
Classifier: Programming Language :: Python :: 3
Classifier: Programming Language :: Python :: 3.8
Classifier: Programming Language :: Python :: 3.9
Classifier: Programming Language :: Python :: 3.10
Classifier: Programming Language :: Python :: 3.11
Classifier: Programming Language :: Python :: 3.10
Classifier: Programming Language :: Python :: 3.11
Classifier: Programming Language :: Python :: 3.7
Classifier: Programming Language :: Python :: 3.8
Classifier: Programming Language :: Python :: 3.9
Classifier: Typing :: Typed
Requires-Dist: aiohttp (>=3.4.0)
Requires-Dist: sd-sdk-python (>=0.2.5)
Requires-Dist: textual[dev] (>=0.27.0,<0.28.0)
